qumeas.libs/libstdc++-d2a021ba.so.6.0.32
qumeas.libs/libgcc_s-f3fb5a36.so.1
qumeas.libs/libgomp-aa3e8c56.so.1.0.0
qumeas/helpers.py
qumeas/libmeas.cpython-39-i386-linux-gnu.so
qumeas/libmeas.cpython-312-i386-linux-musl.so
qumeas/libmeas.cpython-38-i386-linux-gnu.so
qumeas/libmeas.cpython-310-i386-linux-gnu.so
qumeas/pauli_container.py
qumeas/__init__.py
qumeas/state_prep.py
qumeas/cumulant.py
qumeas/_version.py
qumeas/random_measurement.py
qumeas/libmeas.cpython-311-i386-linux-musl.so
qumeas/qiskit_utils/qiskit_helper.py
qumeas/qiskit_utils/qiskitmole.py
qumeas/qiskit_utils/__init__.py
qumeas-0.1.1.data/data/LICENSE
qumeas-0.1.1.data/data/README.md
qumeas-0.1.1.data/data/CMakeLists.txt
qumeas-0.1.1.data/data/VERSION
qumeas-0.1.1.data/data/external/pybind11/CMakeLists.txt
qumeas-0.1.1.data/data/external/pybind11/tests/CMakeLists.txt
qumeas-0.1.1.data/data/external/pybind11/tests/test_cmake_build/CMakeLists.txt
qumeas-0.1.1.data/data/external/pybind11/tests/test_cmake_build/installed_target/CMakeLists.txt
qumeas-0.1.1.data/data/external/pybind11/tests/test_cmake_build/installed_embed/CMakeLists.txt
qumeas-0.1.1.data/data/external/pybind11/tests/test_cmake_build/subdirectory_function/CMakeLists.txt
qumeas-0.1.1.data/data/external/pybind11/tests/test_cmake_build/installed_function/CMakeLists.txt
qumeas-0.1.1.data/data/external/pybind11/tests/test_cmake_build/subdirectory_embed/CMakeLists.txt
qumeas-0.1.1.data/data/external/pybind11/tests/test_cmake_build/subdirectory_target/CMakeLists.txt
qumeas-0.1.1.data/data/external/pybind11/tests/test_embed/CMakeLists.txt
qumeas-0.1.1.data/data/external/eigen/CMakeLists.txt
qumeas-0.1.1.data/data/external/eigen/test/CMakeLists.txt
qumeas-0.1.1.data/data/external/eigen/scripts/CMakeLists.txt
qumeas-0.1.1.data/data/external/eigen/doc/CMakeLists.txt
qumeas-0.1.1.data/data/external/eigen/doc/snippets/CMakeLists.txt
qumeas-0.1.1.data/data/external/eigen/doc/examples/CMakeLists.txt
qumeas-0.1.1.dist-info/top_level.txt
qumeas-0.1.1.dist-info/RECORD
qumeas-0.1.1.dist-info/LICENSE
qumeas-0.1.1.dist-info/METADATA
qumeas-0.1.1.dist-info/WHEEL
