Metadata-Version: 2.1
Name: qumeas
Version: 0.1.1
Summary: A high-performance, multi-threaded, quantum computing library for Pauli measurements.
Home-page: https://github.com/oimeitei/qumeas
Author: Oinam Romesh Meitei
Author-email: oinam.meitei@fau.de
Classifier: Programming Language :: Python :: 3
Classifier: Programming Language :: C++
Classifier: Operating System :: OS Independent
Classifier: License :: OSI Approved :: Apache Software License
Classifier: Topic :: Software Development :: Libraries
Classifier: Topic :: Scientific/Engineering :: Physics
Requires-Python: >=3.8
License-File: LICENSE
Requires-Dist: numpy
Requires-Dist: scipy
Provides-Extra: qiskit
Requires-Dist: qiskit; extra == "qiskit"
Requires-Dist: qiskit-nature; extra == "qiskit"
Requires-Dist: qiskit-aer; extra == "qiskit"
